cocoa_system/DataAugmentation.py
cocoa_system/__init__.py
cocoa_system-0.1.0.dist-info/LICENSE
cocoa_system-0.1.0.dist-info/METADATA
cocoa_system-0.1.0.dist-info/WHEEL
cocoa_system-0.1.0.dist-info/top_level.txt
cocoa_system-0.1.0.dist-info/RECORD
