Metadata-Version: 2.1
Name: cocoa-system
Version: 0.1.0
Summary: COCOA: COrrelation COefficient-Aware Data Augmentation
Home-page: https://github.com/BigDaMa/COCOA
Author: Mahdi Esmailoghli
Author-email: esmailoghli@dbs.uni-hannover.de
License: UNKNOWN
Project-URL: Bug Tracker, https://github.com/BigDaMa/COCOA/issues
Platform: UNKNOWN
Classifier: Programming Language :: Python :: 3
Classifier: License :: OSI Approved :: Apache Software License
Classifier: Operating System :: OS Independent
Requires-Python: >=3.6
License-File: LICENSE
